dnacompiler/Compiler.py
dnacompiler/Constrain.py
dnacompiler/Library.py
dnacompiler/Part.py
dnacompiler/Sequence.py
dnacompiler/__init__.py
dnacompiler/std/__init__.py
dnacompiler/std/promoters.py
dnacompiler/std/random.py
dnacompiler/std/rbss.py
dnacompiler/std/terminators.py
dnacompiler/utils/Alphabet.py
dnacompiler/utils/Conversion.py
dnacompiler/utils/__init__.py
tests/__init__.py
tests/compiler_test.py
tests/library_test.py
tests/random_test.py
dnacompiler-0.0.6.dist-info/METADATA
dnacompiler-0.0.6.dist-info/WHEEL
dnacompiler-0.0.6.dist-info/top_level.txt
dnacompiler-0.0.6.dist-info/RECORD
