Metadata-Version: 2.1
Name: dnacompiler
Version: 0.0.6
Summary: DNA Compiler uses constrain programming to facilitate genetic design.
Home-page: UNKNOWN
Author: Isaac Guerreiro
Author-email: <isaacguerreirocom@gmail.com>
License: UNKNOWN
Keywords: python
Platform: UNKNOWN
